Workbook

Sheet Dashboard
B2: Sales Performance Dashboard
B3: Sample retail dataset · Jan 2024 – Dec 2025
B6: Total Revenue | E6: Total Profit | H6: Total Orders | K6: Overall Margin %
B7: =SUM(Summary!C6:C9) | E7: =SUM(Summary!D6:D9) | H7: =SUM(Summary!B6:B9) | K7: =SUM(Summary!D6:D9)/SUM(Summary!C6:C9)

Sheet Raw Data
A1: OrderID | B1: OrderDate | C1: CustomerName | D1: Region | E1: Category | F1: Product | G1: ShipMode | H1: Quantity | I1: UnitPrice | J1: Discount | K1: Sales | L1: Profit | M1: ProfitMargin
A2: ORD-10470 | B2: 2024-01-01 | C2: Customer 102 | D2: North | E2: Furniture | F2: Chair | G2: Standard Class | H2: 4 | I2: 720.24 | J2: 0 | K2: 2880.96 | L2: 1315.66 | M2: 0.4567
A3: ORD-11541 | B3: 2024-01-01 | C3: Customer 74 | D3: North | E3: Technology | F3: Monitor | G3: First Class | H3: 4 | I3: 394.73 | J3: 0.15 | K3: 1342.08 | L3: 546.81 | M3: 0.4074
A4: ORD-11817 | B4: 2024-01-01 | C4: Customer 183 | D4: South | E4: Furniture | F4: Desk | G4: Second Class | H4: 8 | I4: 743.32 | J4: 0.15 | K4: 5054.58 | L4: 1238.22 | M4: 0.245
A5: ORD-11160 | B5: 2024-01-02 | C5: Customer 58 | D5: North | E5: Technology | F5: Laptop | G5: Second Class | H5: 8 | I5: 598.82 | J5: 0.2 | K5: 3832.45 | L5: 477.06 | M5: 0.1245
A6: ORD-11262 | B6: 2024-01-02 | C6: Customer 47 | D6: South | E6: Furniture | F6: Desk | G6: Standard Class | H6: 11 | I6: 416.67 | J6: 0.1 | K6: 4125.03 | L6: 1202.72 | M6: 0.2916
A7: ORD-11180 | B7: 2024-01-03 | C7: Customer 116 | D7: East | E7: Technology | F7: Printer | G7: First Class | H7: 4 | I7: 874.43 | J7: 0 | K7: 3497.72 | L7: 551.9 | M7: 0.1578
A8: ORD-10301 | B8: 2024-01-03 | C8: Customer 66 | D8: South | E8: Office Supplies | F8: Paper | G8: Standard Class | H8: 1 | I8: 545.75 | J8: 0.15 | K8: 463.89 | L8: 129.15 | M8: 0.2784
A9: ORD-11326 | B9: 2024-01-03 | C9: Customer 67 | D9: West | E9: Furniture | F9: Bookcase | G9: First Class | H9: 5 | I9: 36.96 | J9: 0 | K9: 184.8 | L9: 88.77 | M9: 0.4804
A10: ORD-11590 | B10: 2024-01-03 | C10: Customer 187 | D10: North | E10: Office Supplies | F10: Stapler | G10: Second Class | H10: 4 | I10: 753.55 | J10: 0 | K10: 3014.2 | L10: 985.55 | M10: 0.327
A11: ORD-10110 | B11: 2024-01-03 | C11: Customer 165 | D11: South | E11: Furniture | F11: Table Lamp | G11: Standard Class | H11: 3 | I11: 24.81 | J11: 0.3 | K11: 52.1 | L11: -0.35 | M11: -0.0067
A12: ORD-11812 | B12: 2024-01-03 | C12: Customer 27 | D12: South | E12: Technology | F12: Printer | G12: Standard Class | H12: 5 | I12: 615.39 | J12: 0 | K12: 3076.95 | L12: 685.13 | M12: 0.2227
A13: ORD-10540 | B13: 2024-01-03 | C13: Customer 36 | D13: North | E13: Technology | F13: Wireless Mouse | G13: Standard Class | H13: 9 | I13: 176.12 | J13: 0 | K13: 1585.08 | L13: 682.16 | M13: 0.4304
... A2019: ORD-11509 | B2019: 2025-12-30 | C2019: Customer 184 | D2019: East | E2019: Office Supplies | F2019: Pens (Box) | G2019: First Class | H2019: 6 | I2019: 721 | J2019: 0.1 | K2019: 3893.4 | L2019: 901.54 | M2019: 0.2316

Sheet Summary
A1: Pivot-Style Summary Tables
A2: All values below are live SUMIFS/AVERAGEIFS/COUNTIFS formulas referencing 'Raw Data'. Select this range and Insert > PivotTable for a native pivot if preferred.
A4: Revenue & Profit by Region
A5: Region | B5: Orders | C5: Total Sales | D5: Total Profit | E5: Profit Margin % | F5: Avg Order Value
A6: East | B6: =COUNTIF('Raw Data'!$D$2:$D$2019,A6) | C6: =SUMIF('Raw Data'!$D$2:$D$2019,A6,'Raw Data'!$K$2:$K$2019) | D6: =SUMIF('Raw Data'!$D$2:$D$2019,A6,'Raw Data'!$L$2:$L$2019) | E6: =IFERROR(D6/C6,0) | F6: =IFERROR(C6/B6,0)
A7: North | B7: =COUNTIF('Raw Data'!$D$2:$D$2019,A7) | C7: =SUMIF('Raw Data'!$D$2:$D$2019,A7,'Raw Data'!$K$2:$K$2019) | D7: =SUMIF('Raw Data'!$D$2:$D$2019,A7,'Raw Data'!$L$2:$L$2019) | E7: =IFERROR(D7/C7,0) | F7: =IFERROR(C7/B7,0)
A8: South | B8: =COUNTIF('Raw Data'!$D$2:$D$2019,A8) | C8: =SUMIF('Raw Data'!$D$2:$D$2019,A8,'Raw Data'!$K$2:$K$2019) | D8: =SUMIF('Raw Data'!$D$2:$D$2019,A8,'Raw Data'!$L$2:$L$2019) | E8: =IFERROR(D8/C8,0) | F8: =IFERROR(C8/B8,0)
A9: West | B9: =COUNTIF('Raw Data'!$D$2:$D$2019,A9) | C9: =SUMIF('Raw Data'!$D$2:$D$2019,A9,'Raw Data'!$K$2:$K$2019) | D9: =SUMIF('Raw Data'!$D$2:$D$2019,A9,'Raw Data'!$L$2:$L$2019) | E9: =IFERROR(D9/C9,0) | F9: =IFERROR(C9/B9,0)
A10: Total | B10: =SUM(B6:B9) | C10: =SUM(C6:C9) | D10: =SUM(D6:D9)
A13: Revenue & Profit by Category
A14: Category | B14: Orders | C14: Total Sales | D14: Total Profit | E14: Profit Margin %
A15: Furniture | B15: =COUNTIF('Raw Data'!$E$2:$E$2019,A15) | C15: =SUMIF('Raw Data'!$E$2:$E$2019,A15,'Raw Data'!$K$2:$K$2019) | D15: =SUMIF('Raw Data'!$E$2:$E$2019,A15,'Raw Data'!$L$2:$L$2019) | E15: =IFERROR(D15/C15,0)
A16: Office Supplies | B16: =COUNTIF('Raw Data'!$E$2:$E$2019,A16) | C16: =SUMIF('Raw Data'!$E$2:$E$2019,A16,'Raw Data'!$K$2:$K$2019) | D16: =SUMIF('Raw Data'!$E$2:$E$2019,A16,'Raw Data'!$L$2:$L$2019) | E16: =IFERROR(D16/C16,0)
A17: Technology | B17: =COUNTIF('Raw Data'!$E$2:$E$2019,A17) | C17: =SUMIF('Raw Data'!$E$2:$E$2019,A17,'Raw Data'!$K$2:$K$2019) | D17: =SUMIF('Raw Data'!$E$2:$E$2019,A17,'Raw Data'!$L$2:$L$2019) | E17: =IFERROR(D17/C17,0)
A20: Monthly Sales Trend
A21: Month | B21: Total Sales | C21: Total Profit
A22: 2024-01 | B22: =SUMPRODUCT(('Raw Data'!$B$2:$B$2019>=DATE(2024,01,1))*('Raw Data'!$B$2:$B$2019<EDATE(DATE(2024,01,1),1))*'Raw Data'!$K$2:$K$2019) | C22: =SUMPRODUCT(('Raw Data'!$B$2:$B$2019>=DATE(2024,01,1))*('Raw Data'!$B$2:$B$2019<EDATE(DATE(2024,01,1),1))*'Raw Data'!$L$2:$L$2019)
A23: 2024-02 | B23: =SUMPRODUCT(('Raw Data'!$B$2:$B$2019>=DATE(2024,02,1))*('Raw Data'!$B$2:$B$2019<EDATE(DATE(2024,02,1),1))*'Raw Data'!$K$2:$K$2019) | C23: =SUMPRODUCT(('Raw Data'!$B$2:$B$2019>=DATE(2024,02,1))*('Raw Data'!$B$2:$B$2019<EDATE(DATE(2024,02,1),1))*'Raw Data'!$L$2:$L$2019)
A24: 2024-03 | B24: =SUMPRODUCT(('Raw Data'!$B$2:$B$2019>=DATE(2024,03,1))*('Raw Data'!$B$2:$B$2019<EDATE(DATE(2024,03,1),1))*'Raw Data'!$K$2:$K$2019) | C24: =SUMPRODUCT(('Raw Data'!$B$2:$B$2019>=DATE(2024,03,1))*('Raw Data'!$B$2:$B$2019<EDATE(DATE(2024,03,1),1))*'Raw Data'!$L$2:$L$2019)
A25: 2024-04 | B25: =SUMPRODUCT(('Raw Data'!$B$2:$B$2019>=DATE(2024,04,1))*('Raw Data'!$B$2:$B$2019<EDATE(DATE(2024,04,1),1))*'Raw Data'!$K$2:$K$2019) | C25: =SUMPRODUCT(('Raw Data'!$B$2:$B$2019>=DATE(2024,04,1))*('Raw Data'!$B$2:$B$2019<EDATE(DATE(2024,04,1),1))*'Raw Data'!$L$2:$L$2019)
A26: 2024-05 | B26: =SUMPRODUCT(('Raw Data'!$B$2:$B$2019>=DATE(2024,05,1))*('Raw Data'!$B$2:$B$2019<EDATE(DATE(2024,05,1),1))*'Raw Data'!$K$2:$K$2019) | C26: =SUMPRODUCT(('Raw Data'!$B$2:$B$2019>=DATE(2024,05,1))*('Raw Data'!$B$2:$B$2019<EDATE(DATE(2024,05,1),1))*'Raw Data'!$L$2:$L$2019)
A27: 2024-06 | B27: =SUMPRODUCT(('Raw Data'!$B$2:$B$2019>=DATE(2024,06,1))*('Raw Data'!$B$2:$B$2019<EDATE(DATE(2024,06,1),1))*'Raw Data'!$K$2:$K$2019) | C27: =SUMPRODUCT(('Raw Data'!$B$2:$B$2019>=DATE(2024,06,1))*('Raw Data'!$B$2:$B$2019<EDATE(DATE(2024,06,1),1))*'Raw Data'!$L$2:$L$2019)
A28: 2024-07 | B28: =SUMPRODUCT(('Raw Data'!$B$2:$B$2019>=DATE(2024,07,1))*('Raw Data'!$B$2:$B$2019<EDATE(DATE(2024,07,1),1))*'Raw Data'!$K$2:$K$2019) | C28: =SUMPRODUCT(('Raw Data'!$B$2:$B$2019>=DATE(2024,07,1))*('Raw Data'!$B$2:$B$2019<EDATE(DATE(2024,07,1),1))*'Raw Data'!$L$2:$L$2019)
A29: 2024-08 | B29: =SUMPRODUCT(('Raw Data'!$B$2:$B$2019>=DATE(2024,08,1))*('Raw Data'!$B$2:$B$2019<EDATE(DATE(2024,08,1),1))*'Raw Data'!$K$2:$K$2019) | C29: =SUMPRODUCT(('Raw Data'!$B$2:$B$2019>=DATE(2024,08,1))*('Raw Data'!$B$2:$B$2019<EDATE(DATE(2024,08,1),1))*'Raw Data'!$L$2:$L$2019)
A30: 2024-09 | B30: =SUMPRODUCT(('Raw Data'!$B$2:$B$2019>=DATE(2024,09,1))*('Raw Data'!$B$2:$B$2019<EDATE(DATE(2024,09,1),1))*'Raw Data'!$K$2:$K$2019) | C30: =SUMPRODUCT(('Raw Data'!$B$2:$B$2019>=DATE(2024,09,1))*('Raw Data'!$B$2:$B$2019<EDATE(DATE(2024,09,1),1))*'Raw Data'!$L$2:$L$2019)
A31: 2024-10 | B31: =SUMPRODUCT(('Raw Data'!$B$2:$B$2019>=DATE(2024,10,1))*('Raw Data'!$B$2:$B$2019<EDATE(DATE(2024,10,1),1))*'Raw Data'!$K$2:$K$2019) | C31: =SUMPRODUCT(('Raw Data'!$B$2:$B$2019>=DATE(2024,10,1))*('Raw Data'!$B$2:$B$2019<EDATE(DATE(2024,10,1),1))*'Raw Data'!$L$2:$L$2019)
A32: 2024-11 | B32: =SUMPRODUCT(('Raw Data'!$B$2:$B$2019>=DATE(2024,11,1))*('Raw Data'!$B$2:$B$2019<EDATE(DATE(2024,11,1),1))*'Raw Data'!$K$2:$K$2019) | C32: =SUMPRODUCT(('Raw Data'!$B$2:$B$2019>=DATE(2024,11,1))*('Raw Data'!$B$2:$B$2019<EDATE(DATE(2024,11,1),1))*'Raw Data'!$L$2:$L$2019)
A33: 2024-12 | B33: =SUMPRODUCT(('Raw Data'!$B$2:$B$2019>=DATE(2024,12,1))*('Raw Data'!$B$2:$B$2019<EDATE(DATE(2024,12,1),1))*'Raw Data'!$K$2:$K$2019) | C33: =SUMPRODUCT(('Raw Data'!$B$2:$B$2019>=DATE(2024,12,1))*('Raw Data'!$B$2:$B$2019<EDATE(DATE(2024,12,1),1))*'Raw Data'!$L$2:$L$2019)
A34: 2025-01 | B34: =SUMPRODUCT(('Raw Data'!$B$2:$B$2019>=DATE(2025,01,1))*('Raw Data'!$B$2:$B$2019<EDATE(DATE(2025,01,1),1))*'Raw Data'!$K$2:$K$2019) | C34: =SUMPRODUCT(('Raw Data'!$B$2:$B$2019>=DATE(2025,01,1))*('Raw Data'!$B$2:$B$2019<EDATE(DATE(2025,01,1),1))*'Raw Data'!$L$2:$L$2019)
A35: 2025-02 | B35: =SUMPRODUCT(('Raw Data'!$B$2:$B$2019>=DATE(2025,02,1))*('Raw Data'!$B$2:$B$2019<EDATE(DATE(2025,02,1),1))*'Raw Data'!$K$2:$K$2019) | C35: =SUMPRODUCT(('Raw Data'!$B$2:$B$2019>=DATE(2025,02,1))*('Raw Data'!$B$2:$B$2019<EDATE(DATE(2025,02,1),1))*'Raw Data'!$L$2:$L$2019)
A36: 2025-03 | B36: =SUMPRODUCT(('Raw Data'!$B$2:$B$2019>=DATE(2025,03,1))*('Raw Data'!$B$2:$B$2019<EDATE(DATE(2025,03,1),1))*'Raw Data'!$K$2:$K$2019) | C36: =SUMPRODUCT(('Raw Data'!$B$2:$B$2019>=DATE(2025,03,1))*('Raw Data'!$B$2:$B$2019<EDATE(DATE(2025,03,1),1))*'Raw Data'!$L$2:$L$2019)
A37: 2025-04 | B37: =SUMPRODUCT(('Raw Data'!$B$2:$B$2019>=DATE(2025,04,1))*('Raw Data'!$B$2:$B$2019<EDATE(DATE(2025,04,1),1))*'Raw Data'!$K$2:$K$2019) | C37: =SUMPRODUCT(('Raw Data'!$B$2:$B$2019>=DATE(2025,04,1))*('Raw Data'!$B$2:$B$2019<EDATE(DATE(2025,04,1),1))*'Raw Data'!$L$2:$L$2019)
A38: 2025-05 | B38: =SUMPRODUCT(('Raw Data'!$B$2:$B$2019>=DATE(2025,05,1))*('Raw Data'!$B$2:$B$2019<EDATE(DATE(2025,05,1),1))*'Raw Data'!$K$2:$K$2019) | C38: =SUMPRODUCT(('Raw Data'!$B$2:$B$2019>=DATE(2025,05,1))*('Raw Data'!$B$2:$B$2019<EDATE(DATE(2025,05,1),1))*'Raw Data'!$L$2:$L$2019)
A39: 2025-06 | B39: =SUMPRODUCT(('Raw Data'!$B$2:$B$2019>=DATE(2025,06,1))*('Raw Data'!$B$2:$B$2019<EDATE(DATE(2025,06,1),1))*'Raw Data'!$K$2:$K$2019) | C39: =SUMPRODUCT(('Raw Data'!$B$2:$B$2019>=DATE(2025,06,1))*('Raw Data'!$B$2:$B$2019<EDATE(DATE(2025,06,1),1))*'Raw Data'!$L$2:$L$2019)
A40: 2025-07 | B40: =SUMPRODUCT(('Raw Data'!$B$2:$B$2019>=DATE(2025,07,1))*('Raw Data'!$B$2:$B$2019<EDATE(DATE(2025,07,1),1))*'Raw Data'!$K$2:$K$2019) | C40: =SUMPRODUCT(('Raw Data'!$B$2:$B$2019>=DATE(2025,07,1))*('Raw Data'!$B$2:$B$2019<EDATE(DATE(2025,07,1),1))*'Raw Data'!$L$2:$L$2019)
A41: 2025-08 | B41: =SUMPRODUCT(('Raw Data'!$B$2:$B$2019>=DATE(2025,08,1))*('Raw Data'!$B$2:$B$2019<EDATE(DATE(2025,08,1),1))*'Raw Data'!$K$2:$K$2019) | C41: =SUMPRODUCT(('Raw Data'!$B$2:$B$2019>=DATE(2025,08,1))*('Raw Data'!$B$2:$B$2019<EDATE(DATE(2025,08,1),1))*'Raw Data'!$L$2:$L$2019)
A42: 2025-09 | B42: =SUMPRODUCT(('Raw Data'!$B$2:$B$2019>=DATE(2025,09,1))*('Raw Data'!$B$2:$B$2019<EDATE(DATE(2025,09,1),1))*'Raw Data'!$K$2:$K$2019) | C42: =SUMPRODUCT(('Raw Data'!$B$2:$B$2019>=DATE(2025,09,1))*('Raw Data'!$B$2:$B$2019<EDATE(DATE(2025,09,1),1))*'Raw Data'!$L$2:$L$2019)
A43: 2025-10 | B43: =SUMPRODUCT(('Raw Data'!$B$2:$B$2019>=DATE(2025,10,1))*('Raw Data'!$B$2:$B$2019<EDATE(DATE(2025,10,1),1))*'Raw Data'!$K$2:$K$2019) | C43: =SUMPRODUCT(('Raw Data'!$B$2:$B$2019>=DATE(2025,10,1))*('Raw Data'!$B$2:$B$2019<EDATE(DATE(2025,10,1),1))*'Raw Data'!$L$2:$L$2019)
A44: 2025-11 | B44: =SUMPRODUCT(('Raw Data'!$B$2:$B$2019>=DATE(2025,11,1))*('Raw Data'!$B$2:$B$2019<EDATE(DATE(2025,11,1),1))*'Raw Data'!$K$2:$K$2019) | C44: =SUMPRODUCT(('Raw Data'!$B$2:$B$2019>=DATE(2025,11,1))*('Raw Data'!$B$2:$B$2019<EDATE(DATE(2025,11,1),1))*'Raw Data'!$L$2:$L$2019)
A45: 2025-12 | B45: =SUMPRODUCT(('Raw Data'!$B$2:$B$2019>=DATE(2025,12,1))*('Raw Data'!$B$2:$B$2019<EDATE(DATE(2025,12,1),1))*'Raw Data'!$K$2:$K$2019) | C45: =SUMPRODUCT(('Raw Data'!$B$2:$B$2019>=DATE(2025,12,1))*('Raw Data'!$B$2:$B$2019<EDATE(DATE(2025,12,1),1))*'Raw Data'!$L$2:$L$2019)

Sheet Lookup Demo
A1: Lookup Functions Demo — INDEX / MATCH
A2: Note: XLOOKUP is intentionally not used here because it isn't supported by all Excel/verification environments (older Excel, some viewers). INDEX/MATCH is the portable equivalent and works everywhere XLOOKUP does — swap in XLOOKUP(lookup_value, lookup_array, return_array) directly if your Excel version supports it.
A4: Product Reference Table | E4: Try it — type a product name below:
A5: Product | B5: Category | C5: AvgUnitPrice | E5: Product: | F5: Binder
A6: Binder | B6: Office Supplies | C6: 593.61 | E6: Category (INDEX/MATCH): | F6: =INDEX($B$6:$B$17,MATCH($F$5,$A$6:$A$17,0))
A7: Bookcase | B7: Furniture | C7: 584.85 | E7: Avg Unit Price (INDEX/MATCH): | F7: =INDEX($C$6:$C$17,MATCH($F$5,$A$6:$A$17,0))
A8: Chair | B8: Furniture | C8: 578.77
A9: Desk | B9: Furniture | C9: 608.32
A10: Laptop | B10: Technology | C10: 646.31
A11: Monitor | B11: Technology | C11: 654.81
A12: Paper | B12: Office Supplies | C12: 589.11
A13: Pens (Box) | B13: Office Supplies | C13: 612.58
A14: Printer | B14: Technology | C14: 587.34
A15: Stapler | B15: Office Supplies | C15: 592.64
A16: Table Lamp | B16: Furniture | C16: 584.06
A17: Wireless Mouse | B17: Technology | C17: 597.24
